parserfromgary.py
settings.py
tag.py
mwparallelparserfromgary-1.0.0.dist-info/LICENSE
mwparallelparserfromgary-1.0.0.dist-info/METADATA
mwparallelparserfromgary-1.0.0.dist-info/WHEEL
mwparallelparserfromgary-1.0.0.dist-info/top_level.txt
mwparallelparserfromgary-1.0.0.dist-info/RECORD
