Metadata-Version: 2.1
Name: mwparallelparserfromgary
Version: 1.0.0
Summary: MediaWiki parallel parser
Author-email: Marcin Garnowski <gtrawirr@gmail.com>
Project-URL: Homepage, https://github.com/Trawirr/mwparallelparserfromgary
Keywords: mediawiki,parser,parallel
Classifier: License :: OSI Approved :: MIT License
Classifier: Programming Language :: Python
Classifier: Programming Language :: Python :: 3
Requires-Python: >=3.9
License-File: LICENSE
